drfasyncview/__init__.py
drfasyncview/requests.py
drfasyncview/views.py
drfasyncview-0.2.3.dist-info/LICENSE
drfasyncview-0.2.3.dist-info/WHEEL
drfasyncview-0.2.3.dist-info/METADATA
drfasyncview-0.2.3.dist-info/RECORD
